pygovee/Govee.py
pygovee/__init__.py
pygovee-1.0.2.dist-info/METADATA
pygovee-1.0.2.dist-info/WHEEL
pygovee-1.0.2.dist-info/top_level.txt
pygovee-1.0.2.dist-info/RECORD
